cocotbext/syncserial/__init__.py
cocotbext/syncserial/syncserial.py
cocotbext/syncserial/version.py
cocotbext_syncserial-0.1.1.dist-info/LICENSE
cocotbext_syncserial-0.1.1.dist-info/METADATA
cocotbext_syncserial-0.1.1.dist-info/WHEEL
cocotbext_syncserial-0.1.1.dist-info/top_level.txt
cocotbext_syncserial-0.1.1.dist-info/RECORD
