Metadata-Version: 2.1
Name: cocotbext-syncserial
Version: 0.1.1
Summary: Synchronous Serial modules for cocotb
Home-page: https://github.com/cameronweston/cocotbext-syncserial
Author: Cameron Weston
Author-email: weston.cameron@gmail.com
License: MIT
Download-URL: https://github.com/cameronweston/cocotbext-syncserial/tarball/main
Project-URL: Bug Tracker, https://github.com/cameronweston/cocotbext-syncserial/issues
Project-URL: Source Code, https://github.com/cameronweston/cocotbext-syncserial
Keywords: syncserial,cocotb
Platform: any
Classifier: Development Status :: 3 - Alpha
Classifier: Framework :: cocotb
Classifier: License :: OSI Approved :: MIT License
Classifier: Operating System :: OS Independent
Classifier: Programming Language :: Python :: 3
Classifier: Topic :: Scientific/Engineering :: Electronic Design Automation (EDA)
Requires-Python: >=3.6
License-File: LICENSE
Requires-Dist: cocotb
Provides-Extra: test
Requires-Dist: pytest ; extra == 'test'
Requires-Dist: cocotb-test ; extra == 'test'
